README.md
setup.cfg
setup.py
cufflinks/__init__.py
cufflinks/auth.py
cufflinks/colors.py
cufflinks/datagen.py
cufflinks/date_tools.py
cufflinks/exceptions.py
cufflinks/extract.py
cufflinks/helper.py
cufflinks/offline.py
cufflinks/pandastools.py
cufflinks/plotlytools.py
cufflinks/quant_figure.py
cufflinks/ta.py
cufflinks/themes.py
cufflinks/tools.py
cufflinks/utils.py
cufflinks/version.py
cufflinks.egg-info/PKG-INFO
cufflinks.egg-info/SOURCES.txt
cufflinks.egg-info/dependency_links.txt
cufflinks.egg-info/not-zip-safe
cufflinks.egg-info/pbr.json
cufflinks.egg-info/pkg-info
cufflinks.egg-info/requires.txt
cufflinks.egg-info/top_level.txt