Metadata-Version: 1.0
Name: cufflinks
Version: 0.13.0
Summary: Productivity Tools for Plotly + Pandas
Home-page: https://github.com/santosjorge/cufflinks
Author: Jorge Santos
Author-email: santos.jorge@gmail.com
License: MIT
Keywords: pandas,plotly,plotting
Platform: UNKNOWN
